MANIFEST.in
setup.py
ceilometer_janitor/__init__.py
ceilometer_janitor.egg-info/PKG-INFO
ceilometer_janitor.egg-info/SOURCES.txt
ceilometer_janitor.egg-info/dependency_links.txt
ceilometer_janitor.egg-info/entry_points.txt
ceilometer_janitor.egg-info/top_level.txt
ceilometer_janitor/templates/stop_instance.tpl