Metadata-Version: 1.1
Name: ceilometer-janitor
Version: 0.1.2
Summary: Cleanup vms based on ceilometer stats
Home-page: UNKNOWN
Author: Jorge Niedbalski R.
Author-email: jnr@metaklass.org
License: BSD
Keywords: ceilometer vm stats
Platform: UNKNOWN
Classifier: Development Status :: 3 - Alpha
Classifier: Intended Audience :: Developers
Classifier: Operating System :: Unix 
